feedback_rl_transformers/__init__.py
feedback_rl_transformers/trainer.py
feedback_rl_transformers-0.1.dist-info/METADATA
feedback_rl_transformers-0.1.dist-info/WHEEL
feedback_rl_transformers-0.1.dist-info/top_level.txt
feedback_rl_transformers-0.1.dist-info/RECORD
